{
  "runId": 189,
  "config_id": "189",
  "inputParameters": {
    "simulationType": "Monte-Carlo",
    "maxAllowedBlockchainLength": "25",
    "numberOfMonteCarloRounds": "1",
    "blockchainSystemModelFilePath": "sampling/generated_models/atomsim-189/Net.blockchainsystem",
    "failureThroughputThreshold": "1.0",
    "shannonEntropyK": "1.0",
    "nakamotoCoefficientThreshold": "50.0",
    "reliabilityObservationTimespan": "24.0",
    "config_id": "189",
    "id": "189",
    "validator_count": "542",
    "node_degree": "3",
    "propagation_delay": "21950",
    "block_creation_interval": "931120",
    "max_block_size": "1511521",
    "attacker_hash_power": "0.413964722286907",
    "tie_breaking_parameter": "0.8102859779401071"
  },
  "simulationResult": {
    "simulationParameters": {
      "maxAllowedBlockchainLength": 25,
      "numberOfMonteCarloRounds": 1,
      "blockchainSystemModelFilePath": "sampling/generated_models/atomsim-189/Net.blockchainsystem"
    },
    "threesimSimulationParameters": {
      "failureThroughputThreshold": 1.0,
      "shannonEntropyK": 1.0,
      "nakamotoCoefficientThreshold": 50.0,
      "reliabilityObservationTimespan": 24.0,
      "attackType": "SELFISH_MINING",
      "attackerHashPower": 0.413964722286907,
      "gamma": 0.0,
      "deltaA": 0,
      "deltaB": 0,
      "confirmationDepth": 6,
      "blockInterval": 931120.0,
      "propagationDelay": 21950.0,
      "nodeDegree": 3,
      "maxBlockSize": 1511521,
      "networkBandwidth": 100.0
    },
    "generalResults": [
      {
        "name": "GeographicalDiversity",
        "value": 0.7526849287067744,
        "unit": "%"
      },
      {
        "name": "NakamotoCoefficient",
        "value": 55,
        "unit": "validating nodes"
      }
    ],
    "simulationRoundResults": [
      [
        {
          "name": "AttackSuccessTime",
          "value": -1.0,
          "unit": "ms"
        },
        {
          "name": "Attacker Revenue Share",
          "value": 42.944785276073624,
          "unit": "%"
        },
        {
          "name": "AvailabilityScalability",
          "value": 0.0,
          "unit": "%"
        },
        {
          "name": "AvailabilitySecurity",
          "value": 0.9562902481181675,
          "unit": "%"
        },
        {
          "name": "Consistency",
          "value": 2.85106758E8,
          "unit": "ms"
        },
        {
          "name": "DoubleSpendSuccessProbability",
          "value": 0.5755075221578367
        },
        {
          "name": "FaultTolerance",
          "value": {
            "throughputDelta": {
              "value": 1270382.0837934483,
              "unit": "transactions/min"
            },
            "confirmationLatencyDelta": {
              "value": 3.1761963826923072E7,
              "unit": "ms"
            }
          }
        },
        {
          "name": "Finney Attack Success",
          "value": 0
        },
        {
          "name": "ForkProbability",
          "value": 0.0137200654152132
        },
        {
          "name": "GiniCoefficient",
          "value": 0.0
        },
        {
          "name": "HerfindahlHirschmanIndex",
          "value": 0.0
        },
        {
          "name": "Race Attack Success",
          "value": 0
        },
        {
          "name": "Reliability",
          "value": 0.5674124228228861,
          "unit": "%"
        },
        {
          "name": "ShannonEntropy",
          "value": 6.70834259449676,
          "unit": "bits"
        },
        {
          "name": "StaleBlockRate",
          "value": 4.0,
          "unit": "ratio"
        },
        {
          "name": "TransactionThroughput",
          "value": 0.0,
          "unit": "transactions/min"
        }
      ]
    ],
    "averageSimulationRoundResult": [
      {
        "name": "HerfindahlHirschmanIndex",
        "average": 0.0,
        "standardDeviation": 0.0
      },
      {
        "name": "AttackSuccessTime",
        "average": -1.0,
        "unit": "ms",
        "standardDeviation": 0.0
      },
      {
        "name": "Consistency",
        "average": 2.85106758E8,
        "unit": "ms",
        "standardDeviation": 0.0,
        "coefficientOfVariation": 0.0
      },
      {
        "name": "ShannonEntropy",
        "average": 6.70834259449676,
        "unit": "bits",
        "standardDeviation": 0.0,
        "coefficientOfVariation": 0.0
      },
      {
        "name": "FaultTolerance",
        "average": {
          "throughputDelta": {
            "name": "throughputDelta",
            "average": 1270382.0837934483,
            "unit": "transactions/min",
            "standardDeviation": 0.0,
            "coefficientOfVariation": 0.0
          },
          "confirmationLatencyDelta": {
            "name": "confirmationLatencyDelta",
            "average": 3.1761963826923072E7,
            "unit": "ms",
            "standardDeviation": 0.0,
            "coefficientOfVariation": 0.0
          }
        }
      },
      {
        "name": "DoubleSpendSuccessProbability",
        "average": 0.5755075221578367,
        "standardDeviation": 0.0,
        "coefficientOfVariation": 0.0
      },
      {
        "name": "StaleBlockRate",
        "average": 4.0,
        "unit": "ratio",
        "standardDeviation": 0.0,
        "coefficientOfVariation": 0.0
      },
      {
        "name": "AvailabilityScalability",
        "average": 0.0,
        "unit": "%",
        "standardDeviation": 0.0
      },
      {
        "name": "GiniCoefficient",
        "average": 0.0,
        "standardDeviation": 0.0
      },
      {
        "name": "AvailabilitySecurity",
        "average": 0.9562902481181675,
        "unit": "%",
        "standardDeviation": 0.0,
        "coefficientOfVariation": 0.0
      },
      {
        "name": "ForkProbability",
        "average": 0.0137200654152132,
        "standardDeviation": 0.0,
        "coefficientOfVariation": 0.0
      },
      {
        "name": "TransactionThroughput",
        "average": 0.0,
        "unit": "transactions/min",
        "standardDeviation": 0.0
      },
      {
        "name": "Finney Attack Success",
        "average": 0.0,
        "standardDeviation": 0.0
      },
      {
        "name": "Attacker Revenue Share",
        "average": 42.944785276073624,
        "unit": "%",
        "standardDeviation": 0.0,
        "coefficientOfVariation": 0.0
      },
      {
        "name": "Race Attack Success",
        "average": 0.0,
        "standardDeviation": 0.0
      },
      {
        "name": "Reliability",
        "average": 0.5674124228228861,
        "unit": "%",
        "standardDeviation": 0.0,
        "coefficientOfVariation": 0.0
      }
    ]
  },
  "startSimulationTime": 563157768412375,
  "stopSimulationTime": 563267450955208,
  "simulationTime": 109682542833,
  "memoryUsed": 2850
}